superfastapi/__init__.py
superfastapi/cli.py
superfastapi/decorators.py
superfastapi/exceptions.py
superfastapi/lock.py
superfastapi/resolver.py
superfastapi/serve.py
superfastapi-0.1.3.dist-info/METADATA
superfastapi-0.1.3.dist-info/WHEEL
superfastapi-0.1.3.dist-info/entry_points.txt
superfastapi-0.1.3.dist-info/top_level.txt
superfastapi-0.1.3.dist-info/RECORD
