Metadata-Version: 2.4
Name: superfastapi
Version: 0.1.3
Summary: Build versioned APIs from single-block functions with inline tests, locks, and FastAPI serving.
Author: Chase Anderson
License: MIT
Project-URL: Homepage, https://pypi.org/project/superfastapi/
Keywords: fastapi,api,versioning,pydantic,serverless,superfast
Classifier: Development Status :: 3 - Alpha
Classifier: Intended Audience :: Developers
Classifier: License :: OSI Approved :: MIT License
Classifier: Programming Language :: Python
Classifier: Programming Language :: Python :: 3
Classifier: Programming Language :: Python :: 3.10
Classifier: Programming Language :: Python :: 3.11
Classifier: Programming Language :: Python :: 3.12
Classifier: Topic :: Internet :: WWW/HTTP
Classifier: Topic :: Internet :: WWW/HTTP :: HTTP Servers
Classifier: Framework :: FastAPI
Requires-Python: >=3.10
Requires-Dist: fastapi>=0.111
Requires-Dist: uvicorn>=0.22
Requires-Dist: pydantic>=2.6
Requires-Dist: click>=8.0
Requires-Dist: python-jose[cryptography]>=3.3
